__init__.py
amit_hvac_control/__init__.py
amit_hvac_control/__main__.py
amit_hvac_control/client.py
amit_hvac_control/models.py
amit_hvac_control/api/__init__.py
amit_hvac_control/api/status.py
amit_hvac_control/api/temperature.py
amit_hvac_control/api/utils.py
amit_hvac_control/api/ventilation.py
amit_hvac_control-0.3.3.dist-info/LICENSE
amit_hvac_control-0.3.3.dist-info/METADATA
amit_hvac_control-0.3.3.dist-info/WHEEL
amit_hvac_control-0.3.3.dist-info/top_level.txt
amit_hvac_control-0.3.3.dist-info/RECORD
