Metadata-Version: 2.1
Name: amit_hvac_control
Version: 0.3.3
Summary: Amit HVAC control
Author-email: Mitch Dries <mitch.dries@gmail.com>
Project-URL: Homepage, https://github.com/mitch3s/amit-hvac-control
Project-URL: Issues, https://github.com/mitch3s/amit-hvac-control/issues
Requires-Python: >=3.8
License-File: LICENSE
Requires-Dist: requests
Requires-Dist: bs4
Requires-Dist: asyncio
Requires-Dist: aiohttp >=3.9.5
